swm_example_community_package/ExampleCommunityAgent.py
swm_example_community_package/__init__.py
swm_example_community_package-0.6.0.dev149.dist-info/METADATA
swm_example_community_package-0.6.0.dev149.dist-info/WHEEL
swm_example_community_package-0.6.0.dev149.dist-info/entry_points.txt
swm_example_community_package-0.6.0.dev149.dist-info/RECORD
